demo/__init__.py
demo/fakechat_langchain.py
demo/mockgpt_langchain.py
demo/mockgpt_runnable_langchain.py
demo/openai_langchain.py
demo/fastapi_langchain/__init__.py
demo/fastapi_langchain/main.py
xpuls/__init__.py
xpuls/client/__init__.py
xpuls/client/constants.py
xpuls/client/models.py
xpuls/client/xpuls_client.py
xpuls/mlmonitor/__init__.py
xpuls/mlmonitor/langchain/__init__.py
xpuls/mlmonitor/langchain/instrument.py
xpuls/mlmonitor/langchain/xpuls_client.py
xpuls/mlmonitor/langchain/decorators/__init__.py
xpuls/mlmonitor/langchain/decorators/map_xpuls_project.py
xpuls/mlmonitor/langchain/decorators/telemetry_override_labels.py
xpuls/mlmonitor/langchain/handlers/__init__.py
xpuls/mlmonitor/langchain/handlers/callback_handlers.py
xpuls/mlmonitor/langchain/handlers/constants.py
xpuls/mlmonitor/langchain/patches/__init__.py
xpuls/mlmonitor/langchain/patches/patch_invoke.py
xpuls/mlmonitor/langchain/patches/patch_run.py
xpuls/mlmonitor/langchain/patches/utils.py
xpuls/mlmonitor/langchain/patches/xp_prompt_template.py
xpuls/mlmonitor/langchain/profiling/__init__.py
xpuls/mlmonitor/langchain/profiling/prometheus.py
xpuls/mlmonitor/utils/__init__.py
xpuls/mlmonitor/utils/common.py
xpuls/prompt_hub/__init__.py
xpuls/prompt_hub/prompt.py
xpuls_ml_sdk-0.3.0.dist-info/LICENSE
xpuls_ml_sdk-0.3.0.dist-info/METADATA
xpuls_ml_sdk-0.3.0.dist-info/WHEEL
xpuls_ml_sdk-0.3.0.dist-info/top_level.txt
xpuls_ml_sdk-0.3.0.dist-info/RECORD
